masterzdran_azure_tablestorage_logging/__init__.py
masterzdran_azure_tablestorage_logging/interfaces.py
masterzdran_azure_tablestorage_logging/logger.py
masterzdran_azure_tablestorage_logging/models.py
masterzdran_azure_tablestorage_logging/storage.py
masterzdran_azure_tablestorge_logging-1.0.1.dist-info/LICENSE
masterzdran_azure_tablestorge_logging-1.0.1.dist-info/METADATA
masterzdran_azure_tablestorge_logging-1.0.1.dist-info/WHEEL
masterzdran_azure_tablestorge_logging-1.0.1.dist-info/top_level.txt
masterzdran_azure_tablestorge_logging-1.0.1.dist-info/RECORD
